{
  "filename": "alucard-richter-death-sequences_013.png",
  "source_page": "https://www.castlevaniacrypt.com/sotn-sprites/",
  "source_sheet": "https://www.castlevaniacrypt.com/wp-content/img/sotn/sprites/alucard-richter-death-sequences.png",
  "width": 94,
  "height": 1203,
  "bbox": {
    "x": 1674,
    "y": 52,
    "w": 94,
    "h": 1203
  },
  "palette_hex_list": [
    "#000000",
    "#000060",
    "#0000C0",
    "#030044",
    "#0448C0",
    "#06002C",
    "#072566",
    "#1100C4",
    "#120004",
    "#130060",
    "#200826",
    "#220404",
    "#261408",
    "#2847B0",
    "#2A044B",
    "#2A04B0",
    "#2C0A6D",
    "#330404",
    "#331407",
    "#342008",
    "#354545",
    "#371024",
    "#408000",
    "#432424",
    "#460547",
    "#460B6A",
    "#4C0704",
    "#4C2308",
    "#600503",
    "#621207",
    "#622503",
    "#623008",
    "#630E2A",
    "#660C69",
    "#682010",
    "#711003",
    "#732203",
    "#770000",
    "#773007",
    "#805048",
    "#830000",
    "#831402",
    "#832103",
    "#833207",
    "#841665",
    "#861029",
    "#930200",
    "#932406",
    "#941301",
    "#953208",
    "#A0102B",
    "#A01069",
    "#A04000",
    "#A31001",
    "#A36161",
    "#A42405",
    "#A42829",
    "#A50500",
    "#A83008",
    "#B01810",
    "#B03008",
    "#B21000",
    "#B32104",
    "#B40500",
    "#C60300",
    "#C92704",
    "#CE706F",
    "#D13130",
    "#D24000",
    "#E07070",
    "#E14120",
    "#E26362",
    "#E88078",
    "#F22E25",
    "#F5280E",
    "#F54603",
    "#F60802",
    "#F64224",
    "#F64F45",
    "#F66560",
    "#F6AEAA",
    "#F76551",
    "#F77362",
    "#F84333",
    "#F85234",
    "#F86146",
    "#F88364"
  ]
}