{
  "filename": "blade-soldier-2_004.png",
  "source_page": "https://www.castlevaniacrypt.com/sotn-sprites/",
  "source_sheet": "https://www.castlevaniacrypt.com/wp-content/img/sotn/sprites/blade-soldier-2.png",
  "width": 28,
  "height": 148,
  "bbox": {
    "x": 154,
    "y": 11,
    "w": 28,
    "h": 148
  },
  "palette_hex_list": [
    "#0F080F",
    "#107010",
    "#10A80F",
    "#1F381F",
    "#202020",
    "#40404F",
    "#5F687F",
    "#6F6870",
    "#804000",
    "#8F909F",
    "#B0B8C0",
    "#CF0000",
    "#D0783F",
    "#DFE0EF",
    "#FFB050"
  ]
}