{
  "filename": "bone-halberd-2_001.png",
  "source_page": "https://www.castlevaniacrypt.com/sotn-sprites/",
  "source_sheet": "https://www.castlevaniacrypt.com/wp-content/img/sotn/sprites/bone-halberd-2.gif",
  "width": 118,
  "height": 207,
  "bbox": {
    "x": 119,
    "y": 13,
    "w": 118,
    "h": 207
  },
  "palette_hex_list": [
    "#0F080F",
    "#1F381F",
    "#202020",
    "#3F3750",
    "#40384F",
    "#403F50",
    "#40404F",
    "#4F3F50",
    "#4F4750",
    "#50485F",
    "#505060",
    "#5F5860",
    "#5F687F",
    "#6F6870",
    "#803800",
    "#8F909F",
    "#9F5830",
    "#AF3800",
    "#B0B8C0",
    "#CF0000",
    "#D08020",
    "#DFE0EF",
    "#FF5810",
    "#FF984F"
  ]
}