{
  "filename": "salem-witch-2_000.png",
  "source_page": "https://www.castlevaniacrypt.com/sotn-sprites/",
  "source_sheet": "https://www.castlevaniacrypt.com/wp-content/img/sotn/sprites/salem-witch-2.png",
  "width": 362,
  "height": 473,
  "bbox": {
    "x": 2,
    "y": 3,
    "w": 362,
    "h": 473
  },
  "palette_hex_list": [
    "#181028",
    "#405048",
    "#502040",
    "#5088D0",
    "#582808",
    "#586898",
    "#5870A0",
    "#603840",
    "#6078B0",
    "#6888C0",
    "#6890C8",
    "#6898E0",
    "#708878",
    "#7098D8",
    "#78A8E8",
    "#80A8E0",
    "#88B0E8",
    "#986058",
    "#98B8E8",
    "#A80000",
    "#A8C8F0",
    "#B04818",
    "#B0C0B0",
    "#B0C8F0",
    "#B89090",
    "#B8D0F0",
    "#C8D8F0",
    "#D8D8D8",
    "#D8E8F8",
    "#E07040",
    "#E0E8F8",
    "#E8F0F8",
    "#F0C8B8",
    "#F80000",
    "#F8B068",
    "#F8F8F8"
  ]
}