{
  "filename": "zombie-2_003.png",
  "source_page": "https://www.castlevaniacrypt.com/sotn-sprites/",
  "source_sheet": "https://www.castlevaniacrypt.com/wp-content/img/sotn/sprites/zombie-2.gif",
  "width": 171,
  "height": 119,
  "bbox": {
    "x": 72,
    "y": 12,
    "w": 171,
    "h": 119
  },
  "palette_hex_list": [
    "#000010",
    "#003028",
    "#003830",
    "#005000",
    "#006040",
    "#080800",
    "#085830",
    "#0A0A0A",
    "#105840",
    "#200010",
    "#202020",
    "#280018",
    "#280028",
    "#308060",
    "#308850",
    "#380018",
    "#380020",
    "#380028",
    "#401040",
    "#40C830",
    "#482050",
    "#485050",
    "#48B070",
    "#501850",
    "#502020",
    "#502048",
    "#505050",
    "#506038",
    "#582030",
    "#58D038",
    "#702038",
    "#783010",
    "#905058",
    "#90A860",
    "#90D8B8",
    "#A05840",
    "#A86018",
    "#A89080",
    "#B04848",
    "#B89870",
    "#C89048",
    "#C89058",
    "#C8C8E8",
    "#C8D0E8",
    "#D0D090",
    "#D0D0E0",
    "#D0D0E8"
  ]
}