{
  "filename": "alucard-richter-death-sequences_011.png",
  "source_page": "https://www.castlevaniacrypt.com/sotn-sprites/",
  "width": 194,
  "height": 1272,
  "bbox": {
    "x": 0,
    "y": 0,
    "w": 194,
    "h": 1272
  },
  "palette_hex_list": [
    "#408000",
    "#770000",
    "#F88364",
    "#F64224",
    "#F76551",
    "#832103",
    "#930200",
    "#830000",
    "#A50500",
    "#460547",
    "#B40500",
    "#1100C4",
    "#261408",
    "#220404",
    "#E14120",
    "#732203",
    "#342008",
    "#932406",
    "#4C2308",
    "#622503",
    "#621207",
    "#4C0704",
    "#331407",
    "#2500C8",
    "#2950C8",
    "#C15000",
    "#010052",
    "#1200D5",
    "#2A044B",
    "#4502CC",
    "#130053",
    "#0850C8",
    "#330404",
    "#120004",
    "#C60300",
    "#4058C8",
    "#986868",
    "#315353",
    "#B16665",
    "#F87054",
    "#D18484",
    "#F8C0B8",
    "#415050",
    "#B07068",
    "#E26362",
    "#705050",
    "#0050D5",
    "#CE706F",
    "#F08885",
    "#1550D5",
    "#0000D4",
    "#D34020",
    "#B88888",
    "#F8C4C4",
    "#A42405",
    "#201010",
    "#361014",
    "#E88078",
    "#000000",
    "#C38383",
    "#B32104",
    "#371024",
    "#081818",
    "#0000C0",
    "#B65600",
    "#F85234",
    "#B21000",
    "#F60802",
    "#F5280E",
    "#941301",
    "#B01810",
    "#F84333",
    "#861029",
    "#500826",
    "#2C0A6D",
    "#06002C",
    "#C92704",
    "#F86146",
    "#411326",
    "#660C69",
    "#841070",
    "#623008",
    "#4B3470",
    "#A0102B",
    "#82386A",
    "#460B6A",
    "#773007",
    "#A01069",
    "#A03870",
    "#711003",
    "#831402",
    "#892A2D",
    "#200826",
    "#522225",
    "#630E2A",
    "#F64F45",
    "#F66560",
    "#29336F",
    "#C01068",
    "#E84038",
    "#020074",
    "#D13130",
    "#130070",
    "#F77362",
    "#C0102F",
    "#65326A",
    "#432424",
    "#A31001",
    "#130060",
    "#000060",
    "#782840",
    "#B8B8F8",
    "#88314E",
    "#8C402C",
    "#762323",
    "#030014",
    "#200817",
    "#A01010",
    "#831013",
    "#601112",
    "#A42829",
    "#701015",
    "#A04028",
    "#600503",
    "#600810",
    "#150011",
    "#502232",
    "#F892F8",
    "#342633",
    "#433437",
    "#683010",
    "#F6AEAA"
  ]
}