{
  "filename": "nova-skeleton_000.png",
  "source_page": "https://www.castlevaniacrypt.com/sotn-sprites/",
  "width": 196,
  "height": 257,
  "bbox": {
    "x": 0,
    "y": 0,
    "w": 196,
    "h": 257
  },
  "palette_hex_list": [
    "#546D8E",
    "#5818F8",
    "#00B000",
    "#284840",
    "#083810",
    "#080808",
    "#00E000",
    "#F80000",
    "#F8E0F8",
    "#A0C0F8",
    "#6870F8",
    "#101018",
    "#008808",
    "#086008",
    "#6040F8",
    "#000088",
    "#8098F8",
    "#D0D0F8",
    "#000000",
    "#000040",
    "#2808C0",
    "#FFFFFF",
    "#F7FFFF",
    "#718A8A",
    "#555549",
    "#D8E1E1",
    "#B1BEBE",
    "#C6CFCF",
    "#1C2323",
    "#556969",
    "#233D3D",
    "#E1E1E1",
    "#497A7A",
    "#2BC697",
    "#365959",
    "#869F9B",
    "#A8F3E5"
  ]
}