{
  "filename": "sword-lord_000.png",
  "source_page": "https://www.castlevaniacrypt.com/sotn-sprites/",
  "width": 294,
  "height": 248,
  "bbox": {
    "x": 0,
    "y": 0,
    "w": 294,
    "h": 248
  },
  "palette_hex_list": [
    "#546D8E",
    "#002828",
    "#B87800",
    "#F8B800",
    "#F8F8B8",
    "#505000",
    "#009898",
    "#005028",
    "#080808",
    "#980000",
    "#500000",
    "#080828",
    "#F87800",
    "#202000",
    "#285028",
    "#D8D8B8",
    "#002000",
    "#989878",
    "#F8F8D8",
    "#505050",
    "#787878",
    "#B8B8B8",
    "#202020",
    "#000000",
    "#F8F8F8",
    "#FFFFFF",
    "#F7FFFF",
    "#718A8A",
    "#555549",
    "#D8E1E1",
    "#B1BEBE",
    "#C6CFCF",
    "#1C2323",
    "#556969",
    "#233D3D",
    "#E1E1E1",
    "#497A7A",
    "#2BC697",
    "#365959",
    "#869F9B",
    "#A8F3E5"
  ]
}